kevbits/__init__.py
kevbits/capture_std_stream.py
kevbits/logconfig.py
kevbits/logging/__init__.py
kevbits/logging/duplicate_filter.py
kevbits/math.py
kevbits/misc.py
kevbits/sgconv.py
kevbits-0.11.0.dist-info/METADATA
kevbits-0.11.0.dist-info/WHEEL
kevbits-0.11.0.dist-info/RECORD
